undoom_sketch_mcp/__init__.py
undoom_sketch_mcp/__main__.py
undoom_sketch_mcp/server.py
undoom_sketch_mcp-0.1.4.dist-info/METADATA
undoom_sketch_mcp-0.1.4.dist-info/WHEEL
undoom_sketch_mcp-0.1.4.dist-info/entry_points.txt
undoom_sketch_mcp-0.1.4.dist-info/licenses/LICENSE
undoom_sketch_mcp-0.1.4.dist-info/RECORD
