Metadata-Version: 2.4
Name: undoom-sketch-mcp
Version: 0.1.4
Summary: A MCP server for converting images to sketch effects with multiple styles and batch processing capabilities
Project-URL: Homepage, https://github.com/undoom/undoom-sketch-mcp
Project-URL: Repository, https://github.com/undoom/undoom-sketch-mcp
Project-URL: Issues, https://github.com/undoom/undoom-sketch-mcp/issues
Author-email: Undoom <kaikaihuhu666@163.com>
License: MIT
License-File: LICENSE
Keywords: ai,computer-vision,image-processing,mcp,opencv,sketch
Classifier: Development Status :: 3 - Alpha
Classifier: Intended Audience :: Developers
Classifier: License :: OSI Approved :: MIT License
Classifier: Programming Language :: Python :: 3
Classifier: Programming Language :: Python :: 3.8
Classifier: Programming Language :: Python :: 3.9
Classifier: Programming Language :: Python :: 3.10
Classifier: Programming Language :: Python :: 3.11
Classifier: Programming Language :: Python :: 3.12
Classifier: Programming Language :: Python :: 3.13
Classifier: Topic :: Multimedia :: Graphics :: Graphics Conversion
Classifier: Topic :: Scientific/Engineering :: Image Processing
Requires-Python: >=3.8
Requires-Dist: mcp[cli]>=1.12.3
Requires-Dist: numpy>=1.24.0
Requires-Dist: opencv-python>=4.8.0
